.hgignore
.hgtags
AUTHORS.txt
LICENSE.txt
README.txt
setup.py
cmsplugin_filer_audio/__init__.py
cmsplugin_filer_audio/cms_plugins.py
cmsplugin_filer_audio/models.py
cmsplugin_filer_audio.egg-info/PKG-INFO
cmsplugin_filer_audio.egg-info/SOURCES.txt
cmsplugin_filer_audio.egg-info/dependency_links.txt
cmsplugin_filer_audio.egg-info/entry_points.txt
cmsplugin_filer_audio.egg-info/namespace_packages.txt
cmsplugin_filer_audio.egg-info/not-zip-safe
cmsplugin_filer_audio.egg-info/requires.txt
cmsplugin_filer_audio.egg-info/top_level.txt
cmsplugin_filer_audio/locale/en/LC_MESSAGES/django.po
cmsplugin_filer_audio/locale/es/LC_MESSAGES/django.po
cmsplugin_filer_audio/locale/eu/LC_MESSAGES/django.po
cmsplugin_filer_audio/migrations/0001_initial.py
cmsplugin_filer_audio/migrations/__init__.py
cmsplugin_filer_audio/static/cmsplugin_filer_audio/style.css
cmsplugin_filer_audio/static/cmsplugin_filer_audio/flowplayer/flowplayer-3.2.10.min.js
cmsplugin_filer_audio/static/cmsplugin_filer_audio/flowplayer/flowplayer-3.2.11.swf
cmsplugin_filer_audio/static/cmsplugin_filer_audio/flowplayer/flowplayer.audio-3.2.9.swf
cmsplugin_filer_audio/static/cmsplugin_filer_audio/flowplayer/flowplayer.controls-3.2.11.swf
cmsplugin_filer_audio/templates/cmsplugin_filer_audio/plugin.html
docs/HISTORY.txt