Metadata-Version: 1.0
Name: cmsplugin-filer-audio
Version: 0.2
Summary: MP3 player for Django CMS with flowplayer
Home-page: http://lagunak.gisa-elkartea.org/projects/cmsplugin_filer_audio
Author: GISA Elkartea
Author-email: kontaktua@gisa-elkartea.org
License: GPL3
Platform: UNKNOWN
Classifier: Programming Language :: Python
Classifier: Framework :: Django
Classifier: Topic :: Software Development :: Libraries :: Python Modules
Classifier: License :: OSI Approved :: GNU General Public License v3 or later (GPLv3+)
Classifier: Topic :: Multimedia :: Sound/Audio :: Players
